bs4multiproc/README.MD
bs4multiproc/__init__.py
bs4multiproc/requirements.txt
bs4multiproc/thirdparty.json
bs4multiproc-0.10.dist-info/LICENSE.rst
bs4multiproc-0.10.dist-info/METADATA
bs4multiproc-0.10.dist-info/WHEEL
bs4multiproc-0.10.dist-info/top_level.txt
bs4multiproc-0.10.dist-info/RECORD
