Metadata-Version: 2.1
Name: bs4multiproc
Version: 0.10
Summary: Manages Android packages on a device through DataFrames
Home-page: https://github.com/hansalemaos/bs4multiproc
Author: Johannes Fischer
Author-email: aulasparticularesdealemaosp@gmail.com
License: MIT
Keywords: bs4,DataFrame,webscraping,html,parsing
Classifier: Development Status :: 4 - Beta
Classifier: Programming Language :: Python :: 3 :: Only
Classifier: Programming Language :: Python :: 3.10
Classifier: Topic :: Software Development :: Libraries :: Python Modules
Classifier: Topic :: Utilities
License-File: LICENSE.rst
Requires-Dist: a-pandas-ex-apply-ignore-exceptions
Requires-Dist: beautifulsoup4
Requires-Dist: cchardet
Requires-Dist: fake-headers
Requires-Dist: flatten-any-dict-iterable-or-whatsoever
Requires-Dist: lxml
Requires-Dist: pandas
Requires-Dist: regex
Requires-Dist: requests
